ammico/__init__.py
ammico/colors.py
ammico/cropposts.py
ammico/display.py
ammico/faces.py
ammico/multimodal_search.py
ammico/summary.py
ammico/text.py
ammico/utils.py
ammico/data/Color_tables.csv
ammico/data/test-crop-image.png
ammico/data/ref/ref-00.png
ammico/data/ref/ref-01.png
ammico/data/ref/ref-02.png
ammico/data/ref/ref-03.png
ammico/data/ref/ref-04.png
ammico/data/ref/ref-05.png
ammico/data/ref/ref-06.png
ammico/data/ref/ref-07.png
ammico/data/ref/ref-08.png
ammico/data/ref/ref-09.png
ammico/data/ref/ref-10.png
ammico/data/ref/ref-11.png
ammico/data/ref/ref-12.png
ammico/data/ref/ref-13.png
ammico/data/ref/test.csv
ammico/notebooks/DemoNotebook_ammico.ipynb
ammico/notebooks/cropposts.ipynb
ammico/notebooks/get-text-from-image.ipynb
ammico/test/conftest.py
ammico/test/pytest.ini
ammico/test/test_colors.py
ammico/test/test_cropposts.py
ammico/test/test_display.py
ammico/test/test_faces.py
ammico/test/test_multimodal_search.py
ammico/test/test_summary.py
ammico/test/test_text.py
ammico/test/test_utils.py
ammico/test/data/IMG_2746.png
ammico/test/data/IMG_2809.png
ammico/test/data/IMG_3755.jpg
ammico/test/data/IMG_3756.jpg
ammico/test/data/IMG_3757.jpg
ammico/test/data/IMG_3758.png
ammico/test/data/d755771b-225e-432f-802e-fb8dc850fff7.png
ammico/test/data/example_append_data_to_dict_in.json
ammico/test/data/example_append_data_to_dict_out.json
ammico/test/data/example_dump_df.csv
ammico/test/data/example_faces.json
ammico/test/data/example_summary.txt
ammico/test/data/example_utils_init_dict.json
ammico/test/data/pexels-1000990-1954659.jpg
ammico/test/data/pexels-maksgelatin-4750169.jpg
ammico/test/data/pexels-pixabay-415829.jpg
ammico/test/data/test-utf16.csv
ammico/test/data/test.csv
ammico/test/data/test_data_out.csv
ammico/test/data/test_data_out_nokey.csv
ammico/test/data/test_read_csv_ref.json
ammico/test/data/text_IMG_3755.txt
ammico/test/data/text_IMG_3756.txt
ammico/test/data/text_IMG_3757.txt
ammico/test/data/text_translated_IMG_3755.txt
ammico-0.2.6.dist-info/METADATA
ammico-0.2.6.dist-info/WHEEL
ammico-0.2.6.dist-info/entry_points.txt
ammico-0.2.6.dist-info/licenses/LICENSE
ammico-0.2.6.dist-info/RECORD
