Metadata-Version: 2.4
Name: ammico
Version: 0.2.6
Summary: AI Media and Misinformation Content Analysis Tool
Project-URL: homepage, https://github.com/ssciwr/AMMICO
Project-URL: documentation, https://ssciwr.github.io/AMMICO/build/html/index.html
Maintainer-email: Inga Ulusoy <ssc@iwr.uni-heidelberg.de>, Petr Andriushchenko <ssc@iwr.uni-heidelberg.de>
License: MIT
License-File: LICENSE
Classifier: License :: OSI Approved :: MIT License
Classifier: Operating System :: OS Independent
Classifier: Programming Language :: Python :: 3
Requires-Python: >=3.8
Requires-Dist: ammico-lavis>=1.0.2.3
Requires-Dist: bertopic<=0.14.1
Requires-Dist: colorgram-py
Requires-Dist: colour-science
Requires-Dist: dash-bootstrap-components
Requires-Dist: dash>=2.11.0
Requires-Dist: datasets
Requires-Dist: deepface<=0.0.93
Requires-Dist: google-cloud-vision
Requires-Dist: googletrans==4.0.0rc1
Requires-Dist: grpcio
Requires-Dist: huggingface-hub<=0.25.2
Requires-Dist: importlib-metadata
Requires-Dist: importlib-resources
Requires-Dist: ipython
Requires-Dist: jupyter
Requires-Dist: jupyter-dash
Requires-Dist: matplotlib
Requires-Dist: numpy<=1.23.4
Requires-Dist: pandas
Requires-Dist: peft<=0.13.0
Requires-Dist: pillow
Requires-Dist: pooch
Requires-Dist: protobuf
Requires-Dist: pytest
Requires-Dist: pytest-cov
Requires-Dist: requests
Requires-Dist: retina-face
Requires-Dist: scikit-learn>1.3.0
Requires-Dist: setuptools
Requires-Dist: spacy<=3.7.5
Requires-Dist: tensorflow>=2.13.0
Requires-Dist: torch<2.6.0
Requires-Dist: tqdm
Requires-Dist: transformers
Requires-Dist: webcolors>1.13
